Metadata-Version: 2.1
Name: YaraParser
Version: 1.0.1
Summary: Parse and easily work with Yara rules.
Home-page: https://www.github.com/jrbrawner/YaraParser
Author: Joshua Brawner
Author-email: jrbbrawner@gmail.com
License: Apache Software License
Keywords: yara parser
Classifier: Development Status :: 3 - Alpha
Classifier: Topic :: Utilities
Classifier: License :: OSI Approved :: Apache Software License
Classifier: Programming Language :: Python :: 3
License-File: LICENSE.md
